{
  "id": "luminous3",
  "lang": "chinese",
  "title": "第三端光明奧蹟，耶穌宣佈天國來臨",
  "tts": {
    "voice": "zh-CN-XiaoxiaoNeural",
    "rate": "-5%",
    "input": "text"
  },
  "passages": [
    {
      "passage_id": 1,
      "segments": [
        {
          "passage_segment_id": "1a",
          "text": "第三端光明奧蹟，耶穌宣佈天國來臨.",
          "phonetic": "Dì sān duān guāng míng ào jì, Yē sū xuān bù tiān guó lái lín.",
          "timing": {
            "full": [
              0.103,
              3.589
            ],
            "passage": [
              0.103,
              3.589
            ]
          }
        }
      ]
    }
  ]
}
